<?xml version="1.0" encoding="UTF-8" standalone="yes"?>
<persistence xmlns="https://jakarta.ee/xml/ns/persistence"
             xmlns:xsi="http://www.w3.org/2001/XMLSchema-instance"
             xsi:schemaLocation="https://jakarta.ee/xml/ns/persistence https://jakarta.ee/xml/ns/persistence/persistence_3_0.xsd"
             version="3.0">
  <persistence-unit name="default">

    <class>Entity.EvenementEntity</class>
    <class>Entity.InscriptionEntity</class>
    <class>Entity.LieuEntity</class>
    <class>Entity.MembreEntity</class>
    <properties>
      <property name="hibernate.jdbc.url" value="jdbc:mariadb://obiwan.univ-brest.fr:3306/e21905149_db1"/>
      <property name="hibernate.jdbc.driver" value="org.mariadb.jdbc.Driver"/>
      <property name="hibernate.jdbc.user" value="e21905149sql"/>
      <property name=".jdbc.password" value="YAt8mL09"/>
    </properties>
  </persistence-unit>
</persistence>
